chython_synplan-1.91.dist-info/RECORD
chython_synplan-1.91.dist-info/LICENSE
chython_synplan-1.91.dist-info/WHEEL
chython_synplan-1.91.dist-info/METADATA
chython/_functions.py
chython/__init__.py
chython/exceptions.py
chython/periodictable/groupX.py
chython/periodictable/groupIX.py
chython/periodictable/groupXVIII.py
chython/periodictable/groupIII.py
chython/periodictable/groupV.py
chython/periodictable/groupIV.py
chython/periodictable/groupXIV.py
chython/periodictable/__init__.py
chython/periodictable/groupVI.py
chython/periodictable/groupVIII.py
chython/periodictable/groupXVI.py
chython/periodictable/groupXV.py
chython/periodictable/groupVII.py
chython/periodictable/groupXI.py
chython/periodictable/groupXIII.py
chython/periodictable/groupXII.py
chython/periodictable/groupII.py
chython/periodictable/groupI.py
chython/periodictable/groupXVII.py
chython/periodictable/base/vector.py
chython/periodictable/base/query.py
chython/periodictable/base/__init__.py
chython/periodictable/base/groups.py
chython/periodictable/base/element.py
chython/periodictable/base/dynamic.py
chython/periodictable/base/periods.py
chython/algorithms/__init__.py
chython/algorithms/mcs.py
chython/algorithms/morgan.py
chython/algorithms/_isomorphism.pyx
chython/algorithms/isomorphism.py
chython/algorithms/smiles.py
chython/algorithms/stereo.py
chython/algorithms/x3dom.py
chython/algorithms/rings.py
chython/algorithms/depict.py
chython/algorithms/mapping/attention.py
chython/algorithms/mapping/_reactions.py
chython/algorithms/mapping/__init__.py
chython/algorithms/mapping/groups.py
chython/algorithms/mapping/fixmapper.py
chython/algorithms/mapping/_groups.py
chython/algorithms/test/test_smiles.py
chython/algorithms/test/__init__.py
chython/algorithms/test/test_isomorphism.py
chython/algorithms/calculate2d/molecule.py
chython/algorithms/calculate2d/__init__.py
chython/algorithms/calculate2d/clean2d.js
chython/algorithms/calculate2d/reaction.py
chython/algorithms/tautomers/_base.py
chython/algorithms/tautomers/acid_base.py
chython/algorithms/tautomers/_keto_enol.py
