Metadata-Version: 2.3
Name: chython-synplan
Version: 1.91
Summary: Library for processing molecules and reactions in python way
License: LGPL-3.0-or-later
Author: Ramil Nugmanov
Author-email: nougmanoff@protonmail.com
Requires-Python: >=3.10,<3.13
Classifier: Environment :: Plugins
Classifier: Intended Audience :: Science/Research
Classifier: License :: OSI Approved :: GNU Lesser General Public License v3 or later (LGPLv3+)
Classifier: Operating System :: OS Independent
Classifier: Programming Language :: Python
Classifier: Programming Language :: Python :: 3 :: Only
Classifier: Topic :: Scientific/Engineering
Classifier: Topic :: Scientific/Engineering :: Chemistry
Classifier: Topic :: Scientific/Engineering :: Information Analysis
Classifier: Topic :: Software Development
Classifier: Topic :: Software Development :: Libraries
Classifier: Topic :: Software Development :: Libraries :: Python Modules
Provides-Extra: rdkit
Requires-Dist: cachedmethods (>=0.1.4)
Requires-Dist: lazy-object-proxy (>=1.6)
Requires-Dist: lxml (>=4.1)
Requires-Dist: mini-racer (>=0.12.4)
Requires-Dist: numpy (>=1.26)
Requires-Dist: rdkit (>=2023.9) ; extra == "rdkit"
Project-URL: Documentation, https://chython.readthedocs.io
Project-URL: Homepage, https://github.com/chython/chython
